tpu_tf2/__init__.py
tpu_tf2/tpu.py
tpu_tf2-1.1.0.dist-info/LICENSE
tpu_tf2-1.1.0.dist-info/METADATA
tpu_tf2-1.1.0.dist-info/WHEEL
tpu_tf2-1.1.0.dist-info/top_level.txt
tpu_tf2-1.1.0.dist-info/zip-safe
tpu_tf2-1.1.0.dist-info/RECORD
