Metadata-Version: 2.1
Name: tpu-tf2
Version: 1.1.0
Summary: TPU use in single line in colab.
Home-page: https://github.com/ashishpatel26/tpu_tf2
Author: ashishpatel26
Author-email: ashishpatel.ce.2011@gmail.com
License: UNKNOWN
Keywords: tpu_tf2,tpu,colab tpu,tpu_tf2,TPU,tpu use in single line in colab
Platform: any
Classifier: License :: OSI Approved :: MIT License
Classifier: Programming Language :: Python :: 3
